PrioNet/__init__.py
PrioNet/bybit.py
PrioNet/framework.py
PrioNet/log.py
PrioNet/telegram.py
prionet-0.0.2.dist-info/METADATA
prionet-0.0.2.dist-info/WHEEL
prionet-0.0.2.dist-info/licenses/LICENSE
prionet-0.0.2.dist-info/RECORD
